tiny_torch_mirror/__init__.py
tiny_torch_mirror/__main__.py
tiny_torch_mirror/_interface.py
tiny_torch_mirror/core/__init__.py
tiny_torch_mirror/core/config.py
tiny_torch_mirror/core/fetch.py
tiny_torch_mirror/core/job.py
tiny_torch_mirror/core/log.py
tiny_torch_mirror/core/server.py
tiny_torch_mirror/core/sync.py
tiny_torch_mirror/core/ui.py
tiny_torch_mirror/core/utils.py
tiny_torch_mirror-0.1.3.dist-info/METADATA
tiny_torch_mirror-0.1.3.dist-info/WHEEL
tiny_torch_mirror-0.1.3.dist-info/entry_points.txt
tiny_torch_mirror-0.1.3.dist-info/top_level.txt
tiny_torch_mirror-0.1.3.dist-info/RECORD
